README.md
acl-search
setup.cfg
setup.py
acl_search.egg-info/PKG-INFO
acl_search.egg-info/SOURCES.txt
acl_search.egg-info/dependency_links.txt
acl_search.egg-info/requires.txt
acl_search.egg-info/top_level.txt
acl_search.egg-info/zip-safe
src/__init__.py
src/acl_search.py
src/firewall_filter.py