Metadata-Version: 1.1
Name: acl-search
Version: 1.0.1
Summary: Search through an ACL file to find intersecting destination IPs
Home-page: https://github.com/bwagner5/acl-search
Author: Brandon Wagner
Author-email: brandon@brandonwagner.info
License: MIT
Download-URL: https://github.com/bwagner5/acl-search/archive/1.0.1.tar.gz
Platform: UNKNOWN
